einshape/__init__.py
einshape/src/__init__.py
einshape/src/abstract_ops.py
einshape/src/backend.py
einshape/src/engine.py
einshape/src/optimizer.py
einshape/src/jax/__init__.py
einshape/src/jax/jax_ops.py
einshape/src/numpy/__init__.py
einshape/src/numpy/numpy_ops.py
einshape/src/tensorflow/__init__.py
einshape/src/tensorflow/preprocessing.py
einshape/src/tensorflow/tf_ops.py
einshape-1.0.dist-info/LICENSE
einshape-1.0.dist-info/METADATA
einshape-1.0.dist-info/WHEEL
einshape-1.0.dist-info/top_level.txt
einshape-1.0.dist-info/RECORD
